ofen/__init__.py
ofen/constants.py
ofen/enums.py
ofen/exceptions.py
ofen/logger.py
ofen/pretrainable.py
ofen/types.py
ofen/batch_processor/__init__.py
ofen/batch_processor/batch_generator.py
ofen/batch_processor/batch_processor.py
ofen/batch_processor/generator/__init__.py
ofen/batch_processor/generator/batch_generator.py
ofen/batch_processor/generator/batch_processor.py
ofen/common/__init__.py
ofen/common/gpu_utils.py
ofen/common/hf_utils.py
ofen/common/model_checker.py
ofen/common/numpy_utils.py
ofen/common/onnx_utils.py
ofen/common/ray_utils.py
ofen/common/tensor_utils.py
ofen/common/utils.py
ofen/configs/__init__.py
ofen/configs/optimization_config.py
ofen/configs/base/__init__.py
ofen/configs/base/base_config.py
ofen/models/__init__.py
ofen/models/base/__init__.py
ofen/models/base/cross_encoder.py
ofen/models/base/encoder.py
ofen/models/base/model.py
ofen/models/base/ort_model.py
ofen/models/base/text_encoder.py
ofen/models/mixins/__init__.py
ofen/models/mixins/onnx_exportable.py
ofen/models/mixins/torch_optimizer.py
ofen/models/onnx/__init__.py
ofen/models/onnx/ort_cross_encoder.py
ofen/models/onnx/ort_text_encoder.py
ofen/models/torch/__init__.py
ofen/models/torch/clip_encoder.py
ofen/models/torch/colbert.py
ofen/models/torch/cross_encoder.py
ofen/models/torch/text_encoder.py
ofen/models/torch/layers/__init__.py
ofen/models/torch/layers/activation_layer.py
ofen/models/torch/layers/normalization_layer.py
ofen/models/torch/layers/pooling_layer.py
ofen/processors/__init__.py
ofen/processors/base.py
ofen/processors/colbert_processor.py
ofen/processors/text_processor.py
ofen/runners/__init__.py
ofen/runners/base.py
ofen/runners/ray_runner.py
ofen/runners/runner.py
ofen-0.0.1.dist-info/LICENSE
ofen-0.0.1.dist-info/METADATA
ofen-0.0.1.dist-info/WHEEL
ofen-0.0.1.dist-info/top_level.txt
ofen-0.0.1.dist-info/RECORD
