Metadata-Version: 2.1
Name: ofen
Version: 0.0.1
Summary: Making transformers production ready
Author-email: Julius Lipp <julius@mixedbread.ai>, Rui Huang <rui@mixedbread.ai>
Maintainer-email: Mixedbread AI <info@mixedbread.ai>
License: Apache License
Keywords: AI,Multimodal,Embeddings,Content Understanding
Classifier: Development Status :: 4 - Beta
Classifier: Intended Audience :: Developers
Classifier: License :: OSI Approved :: MIT License
Classifier: Programming Language :: Python :: 3.10
Classifier: Programming Language :: Python :: 3.11
Classifier: Programming Language :: Python :: 3.12
Requires-Python: >=3.9
License-File: LICENSE
Requires-Dist: huggingface-hub >=0.16.4
Requires-Dist: tokenizers >=0.13.3
Requires-Dist: simsimd
Requires-Dist: numpy >=1.20.0
Requires-Dist: jmespath
Provides-Extra: all
Requires-Dist: torch >=1.13.1 ; extra == 'all'
Requires-Dist: transformers >=4.36.2 ; extra == 'all'
Requires-Dist: onnx >=1.15.0 ; extra == 'all'
Requires-Dist: onnxruntime >=1.17.1 ; extra == 'all'
Requires-Dist: onnxsim ; extra == 'all'
Requires-Dist: onnxconverter-common ; extra == 'all'
Requires-Dist: pytest ; extra == 'all'
Requires-Dist: pandas ; extra == 'all'
Requires-Dist: ruff ; extra == 'all'
Requires-Dist: datasets ; extra == 'all'
Provides-Extra: dev
Requires-Dist: pytest ; extra == 'dev'
Requires-Dist: pandas ; extra == 'dev'
Requires-Dist: ruff ; extra == 'dev'
Requires-Dist: datasets ; extra == 'dev'
Requires-Dist: pre-commit ; extra == 'dev'
Provides-Extra: onnx
Requires-Dist: onnx >=1.15.0 ; extra == 'onnx'
Requires-Dist: onnxruntime >=1.17.1 ; extra == 'onnx'
Requires-Dist: onnxsim ; extra == 'onnx'
Requires-Dist: onnxconverter-common ; extra == 'onnx'
Provides-Extra: onnx-gpu
Requires-Dist: onnx >=1.15.0 ; extra == 'onnx-gpu'
Requires-Dist: onnxruntime-gpu >=1.17.1 ; extra == 'onnx-gpu'
Requires-Dist: onnxsim ; extra == 'onnx-gpu'
Requires-Dist: onnxconverter-common ; extra == 'onnx-gpu'
Provides-Extra: torch
Requires-Dist: torch >=1.13.1 ; extra == 'torch'
Requires-Dist: transformers >=4.36.2 ; extra == 'torch'
